gcfpy/__init__.py
gcfpy/app/__init__.py
gcfpy/app/fit_tab.py
gcfpy/app/main_window.py
gcfpy/app/toolbar.py
gcfpy/controllers/__init__.py
gcfpy/controllers/code_generator.py
gcfpy/controllers/data_preprocessing.py
gcfpy/controllers/fit_comparison_manager.py
gcfpy/controllers/fit_control.py
gcfpy/controllers/fit_formula.py
gcfpy/controllers/fit_options.py
gcfpy/controllers/fit_processor.py
gcfpy/controllers/formula_tools.py
gcfpy/controllers/manual_control.py
gcfpy/icon/conf_1d.png
gcfpy/icon/conf_2d.png
gcfpy/icon/decomp.png
gcfpy/icon/resi.png
gcfpy/icon/test.png
gcfpy/utils/__init__.py
gcfpy/utils/config_manager.py
gcfpy/utils/data_loader.py
gcfpy/utils/default_config.json
gcfpy/utils/math_config.json
gcfpy/utils/previous_data.py
gcfpy/widgets/__init__.py
gcfpy/widgets/base_dock.py
gcfpy/widgets/mcmc_plot.py
gcfpy/widgets/plot.py
gcfpy/widgets/plot2d.py
gcfpy/widgets/plot_analysis.py
gcfpy/widgets/tab_manager.py
gcfpy/widgets/xmin_xmax.py
gcfpy-0.1.0.dist-info/licenses/LICENSE
gcfpy-0.1.0.dist-info/METADATA
gcfpy-0.1.0.dist-info/WHEEL
gcfpy-0.1.0.dist-info/entry_points.txt
gcfpy-0.1.0.dist-info/top_level.txt
gcfpy-0.1.0.dist-info/RECORD
