Metadata-Version: 2.4
Name: gcfpy
Version: 0.1.0
Summary: Graphical Curve Fitting GUI for Python
License: MIT License
Project-URL: Homepage, https://github.com/gcfpy/gcfpy
Project-URL: Documentation, https://gcfpy.github.io/gcfpy/
Keywords: fitting,gui,curve fitting,visualization
Requires-Python: >=3.10
License-File: LICENSE
Requires-Dist: PyQt5>=5.15
Requires-Dist: numpy>=1.20
Requires-Dist: pandas>=1.3
Requires-Dist: matplotlib>=3.5
Requires-Dist: lmfit>=1.1
Requires-Dist: scipy>=1.8
Requires-Dist: emcee
Requires-Dist: corner
Requires-Dist: tqdm
Requires-Dist: sympy
Requires-Dist: numdifftools
Requires-Dist: pyqt5-sip
Requires-Dist: sip
Provides-Extra: dev
Requires-Dist: black; extra == "dev"
Requires-Dist: flake8; extra == "dev"
Requires-Dist: isort; extra == "dev"
Requires-Dist: build; extra == "dev"
Requires-Dist: flake8-pyproject; extra == "dev"
Requires-Dist: ruff; extra == "dev"
Provides-Extra: test
Requires-Dist: pytest; extra == "test"
Requires-Dist: pytest-qt; extra == "test"
Requires-Dist: coverage; extra == "test"
Provides-Extra: doc
Requires-Dist: mkdocs; extra == "doc"
Requires-Dist: mkdocs-material; extra == "doc"
Requires-Dist: mkdocstrings[python]; extra == "doc"
Requires-Dist: mkdocs-bootswatch; extra == "doc"
Requires-Dist: mkdocs-mermaid2-plugin; extra == "doc"
Requires-Dist: pymdown-extensions; extra == "doc"
Provides-Extra: hdf5
Requires-Dist: xarray; extra == "hdf5"
Dynamic: license-file
